puregym/__init__.py
puregym/puregym.py
puregym/scraper.py
puregym-0.1.0.dist-info/DESCRIPTION.rst
puregym-0.1.0.dist-info/METADATA
puregym-0.1.0.dist-info/RECORD
puregym-0.1.0.dist-info/WHEEL
puregym-0.1.0.dist-info/metadata.json
puregym-0.1.0.dist-info/top_level.txt
tests/__init__.py
tests/test_puregym.py
