Metadata-Version: 2.0
Name: puregym
Version: 0.1.0
Summary: Module for interacting with PureGym.
Home-page: https://github.com/thomasleese/pypuregym
Author: Thomas Leese
Author-email: thomas@leese.io
License: UNKNOWN
Platform: UNKNOWN
Requires-Dist: requests
Requires-Dist: lxml
Requires-Dist: cssselect
Requires-Dist: esprima
Requires-Dist: cached-property
Requires-Dist: selenium
